battoul_package_lab4_cookie/__init__.py
battoul_package_lab4_cookie/battoul_package_lab4_cookie.py
battoul_package_lab4_cookie-1.0.0.dist-info/LICENCE.txt
battoul_package_lab4_cookie-1.0.0.dist-info/METADATA
battoul_package_lab4_cookie-1.0.0.dist-info/WHEEL
battoul_package_lab4_cookie-1.0.0.dist-info/top_level.txt
battoul_package_lab4_cookie-1.0.0.dist-info/RECORD
