Metadata-Version: 2.1
Name: battoul_package_lab4_cookie
Version: 1.0.0
Summary: An awesome package that does something
Home-page: http://pypi.python.org/pypi/your_package_name/
Author: Elbatoul
Author-email: e.zerga@esi-sba.dz
License: LICENSE.txt
License-File: LICENCE.txt
Requires-Dist: battoul-package-lab4-cookie
